sortvis
