Metadata-Version: 1.0
Name: sortvis
Version: 1.0.2
Summary: Visualized sorting method
Home-page: https://github.com/frank-xjh/Sort-Visualization
Author: frank-xjh
Author-email: frank99-xu@outlook.com
License: MIT
Keywords: sort,method,visual,visualization
Platform: UNKNOWN
